bingbong_api/__init__.py
bingbong_api/client.py
bingbong_api/exceptions.py
bingbong_api/types.py
bingbong_api-0.1.0.dist-info/licenses/LICENSE
bingbong_api-0.1.0.dist-info/METADATA
bingbong_api-0.1.0.dist-info/WHEEL
bingbong_api-0.1.0.dist-info/top_level.txt
bingbong_api-0.1.0.dist-info/RECORD
