Metadata-Version: 2.4
Name: bingbong_api
Version: 0.1.0
Summary: A minimal, typed Python client for the BingBong API.
Home-page: https://example.com/bingbong_api
Author: Your Name
Author-email: you@example.com
Project-URL: Source, https://example.com/bingbong_api
Project-URL: Tracker, https://example.com/bingbong_api/issues
Classifier: Programming Language :: Python :: 3
Classifier: Programming Language :: Python :: 3 :: Only
Classifier: License :: OSI Approved :: MIT License
Classifier: Operating System :: OS Independent
Classifier: Typing :: Typed
Requires-Python: >=3.9
License-File: LICENSE
Requires-Dist: requests<3.0,>=2.28
Dynamic: author
Dynamic: author-email
Dynamic: classifier
Dynamic: description
Dynamic: description-content-type
Dynamic: home-page
Dynamic: license-file
Dynamic: project-url
Dynamic: requires-dist
Dynamic: requires-python
Dynamic: summary
